covid19_il/api_handler/__init__.py
covid19_il/api_handler/consts.py
covid19_il/api_handler/iapi_handler.py
covid19_il/api_handler/api/__init__.py
covid19_il/api_handler/api/api_data_global.py
covid19_il/api_handler/api/api_data_il.py
covid19_il/api_handler/api_factory/__init__.py
covid19_il/api_handler/api_factory/api_enum.py
covid19_il/api_handler/api_factory/api_factory.py
covid19_il/data_handler/__init__.py
covid19_il/data_handler/data_handlers/__init__.py
covid19_il/data_handler/data_handlers/age_gender.py
covid19_il/data_handler/data_handlers/area.py
covid19_il/data_handler/data_handlers/cities.py
covid19_il/data_handler/data_handlers/data_handler.py
covid19_il/data_handler/data_handlers/deaths.py
covid19_il/data_handler/data_handlers/hospitalized.py
covid19_il/data_handler/data_handlers/lab_tests.py
covid19_il/data_handler/data_handlers/medical_staff_morbidity.py
covid19_il/data_handler/data_handlers/quarantine.py
covid19_il/data_handler/data_handlers/recovered.py
covid19_il/data_handler/data_handlers/tested_individuals.py
covid19_il/data_handler/data_handlers/tested_individuals_scores.py
covid19_il/data_handler/data_handlers/young_population.py
covid19_il/data_handler/data_handlers_factory/__init__.py
covid19_il/data_handler/data_handlers_factory/data_handler_factory.py
covid19_il/data_handler/enums/__init__.py
covid19_il/data_handler/enums/area_event.py
covid19_il/data_handler/enums/quarantine_amount.py
covid19_il/data_handler/enums/resource_id.py
covid19_il/logger/__init__.py
covid19_il/logger/logger.py
covid19_il-0.0.1.4.dist-info/LICENSE
covid19_il-0.0.1.4.dist-info/METADATA
covid19_il-0.0.1.4.dist-info/WHEEL
covid19_il-0.0.1.4.dist-info/top_level.txt
covid19_il-0.0.1.4.dist-info/RECORD
