Metadata-Version: 2.1
Name: covid19-il
Version: 0.0.1.4
Summary: python package which brings a "Facade" interface for using official covid19 israeli data gov data.
Home-page: https://github.com/natylaza89/covid19-il
Author: Naty Laza
Author-email: natylaza89@gmail.com
License: MIT
Platform: UNKNOWN
Classifier: License :: OSI Approved :: MIT License
Classifier: Programming Language :: Python :: 3
Classifier: Programming Language :: Python :: 3.8
Requires-Dist: numpy (<2,>=1.19.2)
Requires-Dist: pandas (<2,>=1.1.2)
Requires-Dist: requests (<3,>=2.24.0)
